Configs/__init__.py
Configs/config_base.py
DZDConfigs-1.3.9.dist-info/LICENSE.md
DZDConfigs-1.3.9.dist-info/METADATA
DZDConfigs-1.3.9.dist-info/WHEEL
DZDConfigs-1.3.9.dist-info/top_level.txt
DZDConfigs-1.3.9.dist-info/RECORD
