Metadata-Version: 2.1
Name: DZDConfigs
Version: 1.3.9
Summary: A tiny framework for config management in different environments. Supports configs as classes, .env files, environemt variables
Home-page: https://git.connect.dzd-ev.de/dzdpythonmodules/configs
Author: TB
Author-email: tim.bleimehl@helmholtz-muenchen.de
License: MIT
Requires-Python: >=3.6
License-File: LICENSE.md
Requires-Dist: python-dotenv
